takumi_service/__init__.py
takumi_service/_compat.py
takumi_service/exc.py
takumi_service/log.py
takumi_service/service.py
takumi_service/hook/__init__.py
takumi_service/hook/api.py
takumi_service-0.1.0.dist-info/DESCRIPTION.rst
takumi_service-0.1.0.dist-info/METADATA
takumi_service-0.1.0.dist-info/metadata.json
takumi_service-0.1.0.dist-info/RECORD
takumi_service-0.1.0.dist-info/top_level.txt
takumi_service-0.1.0.dist-info/WHEEL
tests/__init__.py
tests/conftest.py
tests/test_api_hook.py
tests/test_exception.py
tests/test_hook_registry.py
tests/test_log.py
tests/test_service.py
