Metadata-Version: 2.0
Name: takumi-service
Version: 0.1.0
Summary: Takumi service
Home-page: https://github.com/elemecreativelab/takumi-service
Author: Eleme Lab
Author-email: imaralla@icloud.com
License: UNKNOWN
Platform: UNKNOWN
Requires-Dist: takumi-config
Requires-Dist: takumi-thrift
Requires-Dist: gunicorn
Requires-Dist: thriftpy (>=0.3.9)
Requires-Dist: gevent (>=1.2.1)
